pdnl_sana/__init__.py
pdnl_sana/color_deconvolution.py
pdnl_sana/filter.py
pdnl_sana/geo.py
pdnl_sana/image.py
pdnl_sana/interpolate.py
pdnl_sana/logging.py
pdnl_sana/process.py
pdnl_sana/quantify.py
pdnl_sana/requirements.txt
pdnl_sana/slide.py
pdnl_sana/threshold.py
pdnl_sana-1.0.4.dist-info/METADATA
pdnl_sana-1.0.4.dist-info/WHEEL
pdnl_sana-1.0.4.dist-info/licenses/LICENSE
pdnl_sana-1.0.4.dist-info/RECORD
