Metadata-Version: 2.4
Name: pdnl_sana
Version: 1.0.4
Summary: PDNL Semi-Automatic Neuropathology Analyis (SANA)
Project-URL: Homepage, https://github.com/penndigitalneuropathlab/sana
Author-email: Noah Capp <noahmcapp@gmail.com>
License-File: LICENSE
Classifier: Development Status :: 4 - Beta
Classifier: Intended Audience :: Science/Research
Classifier: License :: OSI Approved :: MIT License
Classifier: Operating System :: OS Independent
Classifier: Programming Language :: Python :: 3
Classifier: Topic :: Scientific/Engineering :: Medical Science Apps.
Requires-Python: >=3.9
Requires-Dist: dill
Requires-Dist: matplotlib
Requires-Dist: numba
Requires-Dist: numpy
Requires-Dist: opencv-python
Requires-Dist: openslide-bin
Requires-Dist: openslide-python
Requires-Dist: pillow
Requires-Dist: scipy
Requires-Dist: shapely
